LICENSE.txt
MANIFEST.in
README.rst
setup.py
van/__init__.py
van.static.egg-info/PKG-INFO
van.static.egg-info/SOURCES.txt
van.static.egg-info/dependency_links.txt
van.static.egg-info/namespace_packages.txt
van.static.egg-info/requires.txt
van.static.egg-info/top_level.txt
van/static/__init__.py
van/static/cdn.py
van/static/testing.py
van/static/yui.py
van/static/tests/__init__.py
van/static/tests/test_cdn.py
van/static/tests/test_doctest.py
van/static/tests/test_yui.py
van/static/tests/example/.unix_ignored
van/static/tests/example/example.txt
van/static/tests/example/css/example.css
van/static/tests/example/css/example_imported.css
van/static/tests/example/images/example.jpg
van/static/tests/example/js/example.js