Metadata-Version: 1.1
Name: van.static
Version: 1.3
Summary: Tools for managing Pyramid static files on a CDN
Home-page: http://pypi.python.org/pypi/van.static
Author: Vanguardistas LLC
Author-email: brian@vanguardistas.net
License: BSD-derived
Platform: UNKNOWN
Classifier: Programming Language :: Python :: 2.5
Classifier: Programming Language :: Python :: 2.6
Classifier: Programming Language :: Python :: 2.7
Classifier: Programming Language :: Python :: 3
Classifier: Programming Language :: Python :: 3.2
Classifier: Programming Language :: Python :: 3.3
Classifier: Environment :: Web Environment
Classifier: Intended Audience :: Developers
Classifier: License :: OSI Approved :: BSD License
Classifier: Programming Language :: Python
Classifier: Topic :: Internet :: WWW/HTTP
Classifier: Development Status :: 5 - Production/Stable
Classifier: Framework :: Pyramid
